whash/__init__.py
whash/whash.py
whash-1.0.3.dist-info/LICENSE.txt
whash-1.0.3.dist-info/METADATA
whash-1.0.3.dist-info/WHEEL
whash-1.0.3.dist-info/top_level.txt
whash-1.0.3.dist-info/RECORD
