Metadata-Version: 2.1
Name: whash
Version: 1.0.3
Summary: 开放组件
Home-page: https://github.com/shangxianw/wsxpy
Author: ShangXian Wang
Author-email: 997049907@qq.om
License: UNKNOWN
Platform: UNKNOWN
Classifier: Programming Language :: Python :: 3
Classifier: License :: OSI Approved :: MIT License
Classifier: Operating System :: OS Independent
Requires-Python: >=3.6
